<annotation>
	<folder>image_mask</folder>
	<filename>0013.jpg</filename>
	<path>/home/hamlin/Study/Deep Learning/mask/dataset/image_mask/0013.jpg</path>
	<source>
		<database>Unknown</database>
	</source>
	<size>
		<width>960</width>
		<height>540</height>
		<depth>3</depth>
	</size>
	<segmented>0</segmented>
	<object>
		<name>have_mask</name>
		<pose>Unspecified</pose>
		<truncated>0</truncated>
		<difficult>0</difficult>
		<bndbox>
			<xmin>404</xmin>
			<ymin>102</ymin>
			<xmax>566</xmax>
			<ymax>303</ymax>
		</bndbox>
	</object>
</annotation>
